odoo/addons/l10n_br_stock/README.rst
odoo/addons/l10n_br_stock/__init__.py
odoo/addons/l10n_br_stock/__manifest__.py
odoo/addons/l10n_br_stock/hooks.py
odoo/addons/l10n_br_stock/demo/res_users_demo.xml
odoo/addons/l10n_br_stock/demo/stock_inventory_demo.xml
odoo/addons/l10n_br_stock/demo/stock_location_demo.xml
odoo/addons/l10n_br_stock/i18n/l10n_br_stock.pot
odoo/addons/l10n_br_stock/i18n/pt_BR.po
odoo/addons/l10n_br_stock/models/__init__.py
odoo/addons/l10n_br_stock/models/stock.py
odoo/addons/l10n_br_stock/readme/CONFIGURE.rst
odoo/addons/l10n_br_stock/readme/CONTRIBUTORS.rst
odoo/addons/l10n_br_stock/readme/DESCRIPTION.rst
odoo/addons/l10n_br_stock/readme/INSTALL.rst
odoo/addons/l10n_br_stock/readme/ROADMAP.rst
odoo/addons/l10n_br_stock/readme/USAGE.rst
odoo/addons/l10n_br_stock/static/description/icon.png
odoo/addons/l10n_br_stock/static/description/index.html
odoo/addons/l10n_br_stock/views/stock_view.xml
odoo12_addon_l10n_br_stock-12.0.1.0.0.99.dev19.dist-info/METADATA
odoo12_addon_l10n_br_stock-12.0.1.0.0.99.dev19.dist-info/WHEEL
odoo12_addon_l10n_br_stock-12.0.1.0.0.99.dev19.dist-info/top_level.txt
odoo12_addon_l10n_br_stock-12.0.1.0.0.99.dev19.dist-info/RECORD
